mazing.cpython-312-x86_64-linux-gnu.so
grid/grid.c
grid/grid.h
grid/data_structures/random_container.c
grid/data_structures/random_container.h
grid/data_structures/stack.c
grid/data_structures/stack.h
python_module/mazing.c
python_module/maze_class/maze_class.c
python_module/maze_class/maze_class.h
python_module/tile_class/tile_class.c
python_module/tile_class/tile_class.h
tile/tile.c
tile/tile.h
mazing-0.1.dist-info/LICENSE
mazing-0.1.dist-info/METADATA
mazing-0.1.dist-info/WHEEL
mazing-0.1.dist-info/top_level.txt
mazing-0.1.dist-info/RECORD
