Metadata-Version: 2.2
Name: mazing
Version: 0.1
Summary: Module to generate and interacte with mazes written in C for fast performance.
Author-email: Maksym Khavil <mk.khavil@gmail.com>
Classifier: Programming Language :: Python :: 3
Requires-Python: >=3.10
License-File: LICENSE
